[
  {
    "title": "有银行股半年跌去30% 险资也看走眼了？",
    "url": "http://finance.eastmoney.com/a/202606303788625229.html",
    "content": "银行盈利和分红稳定，高股息属性契合保险投资需求，存量非标到期也有望推动险资继续增持银行股。”国联民生证券银行业首席分析师王先爽判断，未来3年险资增持银行规模预计可达到4000亿元左右。",
    "source_name": "第一财经",
    "source_type": "api",
    "published_at": "2026-07-01",
    "category_hint": "industry",
    "language": "zh",
    "category": "industry",
    "ai_score": 7.9,
    "insurance_relevance": 0.35,
    "ai_tags": [],
    "ai_reason": "市场观察：有银行股半年跌去30% 险资也看走眼了？，有助于理解行业格局。"
  },
  {
    "title": "分红险演示利率上限下调在即，销售人员炒“停售”，真正该看的却不是这个数字",
    "url": "http://insurance.eastmoney.com/a/202607013789269773.html",
    "content": "今年4月下旬，保险业专家在对人身保险产品预定利率研究值进行探讨时，提出当前普通型人身保险产品预定利率研究值为1.93%，这也是时隔五个季度，普通型人身保险产品预定利率研究值首次止跌回升，较上季度的1.89%提升了4个基点。",
    "source_name": "新京报",
    "source_type": "api",
    "published_at": "2026-07-01",
    "category_hint": "product",
    "language": "zh",
    "category": "product",
    "ai_score": 7.7,
    "insurance_relevance": 0.55,
    "ai_tags": [
      "产品"
    ],
    "ai_reason": "市场动态：分红险演示利率上限下调在即，销售人员炒“停售”，真正该看的却，对消费者有参考价值。"
  },
  {
    "title": "银河证券：5月保费增速转负 财产险展现修复态势",
    "url": "http://insurance.eastmoney.com/a/202607013789048063.html",
    "content": "人身险方面，1-5月保险行业实现人身险保费收入2.58万亿元，同比增长5.56%，增幅相较前值（1-4月：6.84%）收窄1.28pp。",
    "source_name": "界面新闻",
    "source_type": "api",
    "published_at": "2026-07-01",
    "category_hint": "product",
    "language": "zh",
    "category": "product",
    "ai_score": 7.4,
    "insurance_relevance": 0.5,
    "ai_tags": [],
    "ai_reason": "市场动态：银河证券：5月保费增速转负 财产险展现修复态势，对消费者有参考价值。"
  },
  {
    "title": "险资QDII额度扩容：上半年17家险企新增13.2亿美元 业内建言额度管理挂钩机构风控能力",
    "url": "http://finance.eastmoney.com/a/202607013789529564.html",
    "content": "“期盼在下半年，会有第二次QDII扩容”，一家保险资管公司人士对财联社记者表示。 数据显示，截至2025年底，券商获批QDII额度较2007年增长近4倍，保险机构QDII额度增长约1.5倍。而同期我国保险资金运用余额从2.7万亿元快速增长至38.5万亿元，增长超13倍。",
    "source_name": "财联社",
    "source_type": "api",
    "published_at": "2026-07-01",
    "category_hint": "industry",
    "language": "zh",
    "category": "industry",
    "ai_score": 7.0,
    "insurance_relevance": 0.35,
    "ai_tags": [],
    "ai_reason": "市场观察：险资QDII额度扩容：上半年17家险企新增13.2亿美元 业，有助于理解行业格局。"
  },
  {
    "title": "高演示收益“挤水分” 保险机构密集下架或调整分红险产品",
    "url": "http://finance.eastmoney.com/a/202606303788705597.html",
    "content": "“实际收益与收益预期不符”是近年来客户投诉分红型保险产品较为集中的理由之一。部分销售代理人拿最高演示利率给客户“算账”，往往让客户形成高预期。",
    "source_name": "新华财经",
    "source_type": "api",
    "published_at": "2026-06-30",
    "category_hint": "product",
    "language": "zh",
    "category": "product",
    "ai_score": 6.9,
    "insurance_relevance": 0.5,
    "ai_tags": [
      "产品"
    ],
    "ai_reason": "产品创新：高演示收益“挤水分” 保险机构密集下架或调整分红险产品，反映保险产品设计新方向。"
  },
  {
    "title": "【读财报】中小金融机构减量提质观察——寿险篇：问题机构出清 偿付能力企稳",
    "url": "http://insurance.eastmoney.com/a/202606303787239020.html",
    "content": "2026年一季度末，保险公司平均综合偿付能力充足率为181%，核心偿付能力充足率为131.9%，高于100%和50%的监管标准。其中，人身险公司分别为170.7%、118.1%。",
    "source_name": "新华财经",
    "source_type": "api",
    "published_at": "2026-06-30",
    "category_hint": "regulation",
    "language": "zh",
    "category": "regulation",
    "ai_score": 6.8,
    "insurance_relevance": 0.45,
    "ai_tags": [
      "监管"
    ],
    "ai_reason": "监管动态：【读财报】中小金融机构减量提质观察——寿险篇：问题机构出清 ，涉及行业合规与风险管理。"
  },
  {
    "title": "上海科技保险加速：保费激增、AI卡位，险企抢占新赛道",
    "url": "http://finance.eastmoney.com/a/202606303788554273.html",
    "content": "今年3月，金融监管总局等部门联合印发《关于加快推动科技保险高质量发展有力支撑高水平科技自立自强的若干意见》，要求建立涵盖科技创新全链条全周期的保险产品和服务体系，并支持上海作为科技保险创新“首发地”之一。 多家在沪保险机构披露的数据显示，科技保险保费增速显著。",
    "source_name": "21世纪经济报道",
    "source_type": "api",
    "published_at": "2026-06-30",
    "category_hint": "research",
    "language": "zh",
    "category": "research",
    "ai_score": 6.7,
    "insurance_relevance": 0.65,
    "ai_tags": [],
    "ai_reason": "技术前沿：上海科技保险加速：保费激增、AI卡位，险企抢占新赛道，推动行业数字化转型。"
  },
  {
    "title": "为科技创新装上“保险芯” 中国太保夯实金融支撑",
    "url": "http://finance.eastmoney.com/a/202606303787088525.html",
    "content": "建设科技强国，离不开市场化风险分担体系保驾护航。保险业积极发挥风险管理功能，为实现高水平科技自立自强夯实金融支撑。 助力机器人量产落地、护航空中生命救援、赋能农业育种转化……中国太保不断提升保险服务质效，为科技创新装上“保险芯”，以科技金融活水滋养新质生产力。",
    "source_name": "证券时报",
    "source_type": "api",
    "published_at": "2026-06-30",
    "category_hint": "research",
    "language": "zh",
    "category": "research",
    "ai_score": 6.7,
    "insurance_relevance": 0.4,
    "ai_tags": [],
    "ai_reason": "研究洞察：为科技创新装上“保险芯” 中国太保夯实金融支撑，为行业创新提供支撑。"
  },
  {
    "title": "甘肃金融监管局：推动古树名木综合保险产品落地",
    "url": "http://insurance.eastmoney.com/a/202606293786903640.html",
    "content": "北京商报讯6月29日，甘肃金融监管局表示，该局指导财险公司加强与林业部门工作联动，创新开发古树名木综合保险产品，开展古树名木“保险+认养”双轨服务模式，保险责任涵盖物化成本、救援维护、第三者风险保障等方面，为绿色“活化石”系上坚实保险带。",
    "source_name": "北京商报",
    "source_type": "api",
    "published_at": "2026-06-29",
    "category_hint": "product",
    "language": "zh",
    "category": "product",
    "ai_score": 6.6,
    "insurance_relevance": 0.65,
    "ai_tags": [
      "产品"
    ],
    "ai_reason": "产品创新：甘肃金融监管局：推动古树名木综合保险产品落地，反映保险产品设计新方向。"
  },
  {
    "title": "中国人保股东会回应热点：全年分红97亿元 子公司计划发债130亿元",
    "url": "http://finance.eastmoney.com/a/202606303788683331.html",
    "content": "《中国经营报》记者注意到，近日，中国人保（601319.SH）召开2025年度股东会议，相关高管参加了会议，并回应了热点问题。",
    "source_name": "中国经营报",
    "source_type": "akshare",
    "published_at": "2026-06-30",
    "category_hint": "industry",
    "language": "zh",
    "category": "industry",
    "ai_score": 6.5,
    "insurance_relevance": 0.4,
    "ai_tags": [],
    "ai_reason": "行业风向：中国人保股东会回应热点：全年分红97亿元 子公司计划发债13，反映保险行业发展趋势。"
  },
  {
    "title": "1-5月全国农业保险已赔付370亿元 金融监管总局指导保险业做好夏粮农险理赔工作",
    "url": "http://insurance.eastmoney.com/a/202606273785442966.html",
    "content": "中证报中证网讯记者近日获悉，金融监管总局系统推动保险业加大农业保险理赔力度，提升服务水平，有效发挥农业保险经济补偿功能，最大限度降低农业生产损失，稳定农民收益，提高投保农户满意度。2026年1—5月，全国农业保险已赔付370亿元，受益农户1209万户次。",
    "source_name": "中国证券报·中证网",
    "source_type": "api",
    "published_at": "2026-06-27",
    "category_hint": "claims",
    "language": "zh",
    "category": "claims",
    "ai_score": 6.2,
    "insurance_relevance": 0.65,
    "ai_tags": [
      "理赔"
    ],
    "ai_reason": "理赔动态：1-5月全国农业保险已赔付370亿元 金融监管总局指导保险业，展示保险服务实践。"
  },
  {
    "title": "资金沉下去 丰收托起来",
    "url": "http://finance.eastmoney.com/a/202606303787106778.html",
    "content": "金融监管部门积极推动保险业加大农业保险理赔力度，提升服务水平，有效发挥农业保险经济补偿功能，最大限度降低农业生产损失，稳定农民收益，提高投保农户满意度。金融监管总局的数据显示，今年前5个月，全国农业保险已赔付370亿元，受益农户1209万户次。",
    "source_name": "经济日报",
    "source_type": "api",
    "published_at": "2026-06-30",
    "category_hint": "claims",
    "language": "zh",
    "category": "claims",
    "ai_score": 6.2,
    "insurance_relevance": 0.55,
    "ai_tags": [
      "理赔"
    ],
    "ai_reason": "理赔动态：资金沉下去 丰收托起来，展示保险服务实践。"
  },
  {
    "title": "去年提供15.9万亿元风险保障！上海科技保险多点护航科创发展",
    "url": "http://finance.eastmoney.com/a/202606283785613342.html",
    "content": "2024年，上海财险业牵头成立了上海市科技保险工作专班，人保财险、平安产险、太保产险、国寿财险等多家在沪险企先后设立科技保险专营机构或组织。同年发布的《上海科技保险产品目录》构建覆盖科技活动全过程的科技保险产品体系，形成170余个产品矩阵。",
    "source_name": "第一财经",
    "source_type": "api",
    "published_at": "2026-06-28",
    "category_hint": "research",
    "language": "zh",
    "category": "research",
    "ai_score": 6.2,
    "insurance_relevance": 0.55,
    "ai_tags": [],
    "ai_reason": "技术前沿：去年提供15.9万亿元风险保障！上海科技保险多点护航科创发展，推动行业数字化转型。"
  },
  {
    "title": "金融监管总局党委书记、局长丁向群带队赴广东调研",
    "url": "http://finance.eastmoney.com/a/202606293786697715.html",
    "content": "6月25日至26日，金融监管总局党委书记、局长丁向群带队赴广东调研，拜会省委、省政府主要负责同志，主持召开金融管理部门座谈会和金融机构座谈会，深入了解当前经济金融形势，特别是中央金融政策贯彻落实、金融风险防控以及严监管强监管等情况，广泛听取各方面意见建议，并看望慰问广东监管局干部职工",
    "source_name": "第一财经",
    "source_type": "api",
    "published_at": "2026-06-29",
    "category_hint": "regulation",
    "language": "zh",
    "category": "regulation",
    "ai_score": 6.1,
    "insurance_relevance": 0.5,
    "ai_tags": [
      "监管",
      "政策"
    ],
    "ai_reason": "监管动态：金融监管总局党委书记、局长丁向群带队赴广东调研，涉及行业合规与风险管理。"
  },
  {
    "title": "分红险演示利率上限调降在即 营销端再现“倒计时”式炒作",
    "url": "http://insurance.eastmoney.com/a/202606293786954134.html",
    "content": "“相比之下，预定利率才是决定保底收益的关键，直接影响到保险产品的定价。”龙格说。保险产品预定利率是保险公司定价时假设的回报率，直接影响保费高低和收益预期，预定利率下降会导致保费上涨。",
    "source_name": "上海证券报·中国证券网",
    "source_type": "api",
    "published_at": "2026-06-29",
    "category_hint": "product",
    "language": "zh",
    "category": "product",
    "ai_score": 6.0,
    "insurance_relevance": 0.5,
    "ai_tags": [
      "产品"
    ],
    "ai_reason": "产品创新：分红险演示利率上限调降在即 营销端再现“倒计时”式炒作，反映保险产品设计新方向。"
  },
  {
    "title": "保险业前5个月“成绩单”出炉！人身险单月走弱、产险整体承压",
    "url": "http://insurance.eastmoney.com/a/202606283785615647.html",
    "content": "财产险方面，整体呈现负增长；人身险方面，虽然整体仍维持正增长，但5月单月出现了负增长。在业内人士看来，5月人身险保费出现负增长，主要是受上年同期基数较高影响，此前的“开门红”也透支了一定投保需求。",
    "source_name": "北京商报",
    "source_type": "api",
    "published_at": "2026-06-28",
    "category_hint": "product",
    "language": "zh",
    "category": "product",
    "ai_score": 6.0,
    "insurance_relevance": 0.5,
    "ai_tags": [],
    "ai_reason": "市场动态：保险业前5个月“成绩单”出炉！人身险单月走弱、产险整体承压，对消费者有参考价值。"
  },
  {
    "title": "金融监管总局指导保险业积极做好夏粮农险理赔",
    "url": "http://finance.eastmoney.com/a/202606263784833160.html",
    "content": "国家金融监督管理总局（以下简称“金融监管总局”）系统积极推动保险业加大农业保险理赔力度，提升服务水平，有效发挥农业保险经济补偿功能，最大限度降低农业生产损失，稳定农民收益，提高投保农户满意度。",
    "source_name": "中国经营报",
    "source_type": "api",
    "published_at": "2026-06-26",
    "category_hint": "claims",
    "language": "zh",
    "category": "claims",
    "ai_score": 5.9,
    "insurance_relevance": 0.6,
    "ai_tags": [
      "理赔"
    ],
    "ai_reason": "消费者权益：金融监管总局指导保险业积极做好夏粮农险理赔，了解理赔服务最新动态。"
  },
  {
    "title": "夏粮收获遇灾害考验，金融监管总局专项调度疏通农险理赔堵点",
    "url": "http://finance.eastmoney.com/a/202606253782849920.html",
    "content": "6月24日，记者从国家金融监管总局获悉，今年以来全国农险赔付保障力度持续加大，有效对冲农业灾害损失。 当前，我国黄淮海等夏粮主产区进入集中收获关键阶段。面对比较集中的区域性大面积农业灾害，社会关注度高，农险理赔服务领域还存在不少困难和问题。",
    "source_name": "第一财经",
    "source_type": "api",
    "published_at": "2026-06-25",
    "category_hint": "regulation",
    "language": "zh",
    "category": "regulation",
    "ai_score": 5.9,
    "insurance_relevance": 0.6,
    "ai_tags": [
      "监管"
    ],
    "ai_reason": "政策风向：夏粮收获遇灾害考验，金融监管总局专项调度疏通农险理赔堵点，影响保险公司经营策略。"
  },
  {
    "title": "北京金融监管局：做好汛期相关灾害应对和保险理赔服务工作",
    "url": "http://insurance.eastmoney.com/a/202606103766857188.html",
    "content": "上证报中国证券网讯（记者韩宋辉）北京金融监管局6月10日发布《关于用好保险保障实现平稳度汛的消费者风险提示》，部署保险机构切实做好汛期相关灾害应对和保险理赔服务工作。 针对汛期高频风险，风险提示提醒，广大消费者可结合自身生产生活场景，合理选配对应保险产品。",
    "source_name": "上海证券报·中国证券网",
    "source_type": "api",
    "published_at": "2026-06-10",
    "category_hint": "claims",
    "language": "zh",
    "category": "claims",
    "ai_score": 5.8,
    "insurance_relevance": 0.7,
    "ai_tags": [
      "理赔"
    ],
    "ai_reason": "理赔动态：北京金融监管局：做好汛期相关灾害应对和保险理赔服务工作，展示保险服务实践。"
  },
  {
    "title": "2026年一季度上海科技保险为企业提供风险保障超5万亿元",
    "url": "http://finance.eastmoney.com/a/202606293786534876.html",
    "content": "上证报中国证券网讯（记者何奎）记者获悉，为呈现上海保险业在科技金融领域的创新实践成果，展现保险服务上海“五个中心”建设与科技自立自强战略的具体路径与协同价值，“奋进‘十五五’ 科技保险助力上海‘五个中心’建设”新闻通气会近日举办。",
    "source_name": "上海证券报·中国证券网",
    "source_type": "api",
    "published_at": "2026-06-29",
    "category_hint": "research",
    "language": "zh",
    "category": "research",
    "ai_score": 5.8,
    "insurance_relevance": 0.45,
    "ai_tags": [],
    "ai_reason": "技术前沿：2026年一季度上海科技保险为企业提供风险保障超5万亿元，推动行业数字化转型。"
  },
  {
    "title": "领跑金融业！中国人寿通过可信数据空间可信能力测评",
    "url": "http://finance.eastmoney.com/a/202606303788273265.html",
    "content": "中国人寿保险股份有限公司（以下简称“中国人寿”，股票代码：601628.SH，2628.HK）建设的“中国人寿企业可信数据空间”顺利通过测评，全面满足技术能力可信、运营治理可信、合规保障可信三大层面要求，使其成为通过测评的14家单位之一，也是其中唯一的金融机构。",
    "source_name": "中国经济网",
    "source_type": "akshare",
    "published_at": "2026-06-30",
    "category_hint": "industry",
    "language": "zh",
    "category": "industry",
    "ai_score": 5.7,
    "insurance_relevance": 0.4,
    "ai_tags": [],
    "ai_reason": "市场观察：领跑金融业！中国人寿通过可信数据空间可信能力测评，有助于理解行业格局。"
  },
  {
    "title": "外资机构展望下半年：稳健基本面为风险资产提供支撑",
    "url": "http://finance.eastmoney.com/a/202606293785640614.html",
    "content": "展望下半年，多家外资机构认为，尽管波动风险犹存，但稳健基本面仍为风险资产提供了支撑，而能源相关大宗商品有望发挥关键的分散配置作用。 富达国际认为，尽管全球市场面临高度波动的环境，但基本面仍为风险资产提供支持。",
    "source_name": "上海证券报",
    "source_type": "api",
    "published_at": "2026-06-29",
    "category_hint": "industry",
    "language": "zh",
    "category": "industry",
    "ai_score": 5.6,
    "insurance_relevance": 0.4,
    "ai_tags": [
      "市场"
    ],
    "ai_reason": "行业风向：外资机构展望下半年：稳健基本面为风险资产提供支撑，反映保险行业发展趋势。"
  },
  {
    "title": "创益通二审胜诉获赔1517万元 被告停产偿付能力存疑",
    "url": "http://finance.eastmoney.com/a/202606303788335639.html",
    "content": "与一审判决相比，二审判决的主要变化如下： 公告指出，根据公司了解的情况，被告江门罗马仕已出现停工停产情形，且涉及多起诉讼，其偿付能力存在重大不确定性。 2026年一季度，创益通实现收入1.36亿元，归母净利润-643万元。",
    "source_name": "财中社",
    "source_type": "api",
    "published_at": "2026-06-30",
    "category_hint": "regulation",
    "language": "zh",
    "category": "regulation",
    "ai_score": 5.6,
    "insurance_relevance": 0.4,
    "ai_tags": [],
    "ai_reason": "监管动态：创益通二审胜诉获赔1517万元 被告停产偿付能力存疑，涉及行业合规与风险管理。"
  },
  {
    "title": "前5月全国农业保险已赔付370亿元",
    "url": "http://insurance.eastmoney.com/a/202606253782816253.html",
    "content": "记者从金融监管总局获悉，该系统积极推动保险业加大农业保险理赔力度，最大限度降低农业生产损失，2026年1-5月，全国农业保险已赔付370亿元，受益农户1209万户次。",
    "source_name": "上海证券报·中国证券网",
    "source_type": "api",
    "published_at": "2026-06-25",
    "category_hint": "claims",
    "language": "zh",
    "category": "claims",
    "ai_score": 5.5,
    "insurance_relevance": 0.5,
    "ai_tags": [
      "理赔"
    ],
    "ai_reason": "消费者权益：前5月全国农业保险已赔付370亿元，了解理赔服务最新动态。"
  },
  {
    "title": "健康险换道竞速：不仅要卖好保险 还要做好健康管理",
    "url": "http://finance.eastmoney.com/a/202606243780165089.html",
    "content": "业内人士认为，加强健康管理业务的发展，有助于解决传统健康险投保易、理赔难、服务弱的行业痛点，险企也能通过健康管理实现风险减量，提升健康险业务的可持续性。",
    "source_name": "中国证券报",
    "source_type": "api",
    "published_at": "2026-06-24",
    "category_hint": "product",
    "language": "zh",
    "category": "product",
    "ai_score": 5.5,
    "insurance_relevance": 0.5,
    "ai_tags": [],
    "ai_reason": "产品创新：健康险换道竞速：不仅要卖好保险 还要做好健康管理，反映保险产品设计新方向。"
  },
  {
    "title": "商务部等9部门：创新优化车险产品供给，探索“车电分离”保险模式",
    "url": "http://insurance.eastmoney.com/a/202606233779581391.html",
    "content": "落实《关于深化改革加强监管促进新能源车险高质量发展的指导意见》，进一步提升车险保障能力和服务水平，建立保险车型综合分级制度。创新优化车险产品供给，提供“基本+变动”的组合产品，探索“车电分离”保险模式。",
    "source_name": "第一财经",
    "source_type": "api",
    "published_at": "2026-06-23",
    "category_hint": "product",
    "language": "zh",
    "category": "product",
    "ai_score": 5.5,
    "insurance_relevance": 0.55,
    "ai_tags": [
      "产品"
    ],
    "ai_reason": "市场动态：商务部等9部门：创新优化车险产品供给，探索“车电分离”保险模，对消费者有参考价值。"
  },
  {
    "title": "华汇人寿：6款分红型保险产品2025年度不进行红利分配，红利实现率为0%",
    "url": "http://insurance.eastmoney.com/a/202606183776445269.html",
    "content": "北京商报讯了解到，华汇人寿保险股份有限公司近日发布公告称，根据2025年度公司分红保险业务的实际经营情况，公司分红型保险产品2025年度不进行红利分配，红利实现率为0%。公司会按照保险合同的约定承担保险责任，履行各项保险金的给付，并持续做好售后服务工作。",
    "source_name": "北京商报",
    "source_type": "api",
    "published_at": "2026-06-18",
    "category_hint": "product",
    "language": "zh",
    "category": "product",
    "ai_score": 5.4,
    "insurance_relevance": 0.5,
    "ai_tags": [
      "产品"
    ],
    "ai_reason": "市场动态：华汇人寿：6款分红型保险产品2025年度不进行红利分配，红利，对消费者有参考价值。"
  },
  {
    "title": "Momenta孖展获8倍认购，公私募与险资顶流集体站台，物理AI赛道升温",
    "url": "http://finance.eastmoney.com/a/202606303788688379.html",
    "content": "高毅资产、博裕资本两家顶级私募，广发基金、华夏基金两家头部公募，以及中国太平洋保险这一险资领军者，每家均出资1000万美元，再加上苏州摩速，中资背景投资者合计占据基石阵容的半壁江山。 这一配置在近年港股IPO中并不多见。尤其值得关注的是险资的参与。",
    "source_name": "财联社",
    "source_type": "api",
    "published_at": "2026-06-30",
    "category_hint": "industry",
    "language": "zh",
    "category": "industry",
    "ai_score": 5.4,
    "insurance_relevance": 0.35,
    "ai_tags": [],
    "ai_reason": "行业风向：Momenta孖展获8倍认购，公私募与险资顶流集体站台，物理，反映保险行业发展趋势。"
  },
  {
    "title": "“车电分离”保险加速探路，重塑新能源车险定价逻辑",
    "url": "http://insurance.eastmoney.com/a/202606243781697043.html",
    "content": "当前，新能源车险面临“车主喊贵，险企叫亏”的难题，而“车电分离”模式的汽车商业车险，被视为重塑新能源车险定价逻辑的模式之一。在业内看来，“车电分离”模式为行业破局与消费者减负提供了一条新路径，通过将车辆与动力电池作为独立标的物进行销售与承保，能够使车险定价更精细、更公平。",
    "source_name": "北京商报",
    "source_type": "api",
    "published_at": "2026-06-24",
    "category_hint": "product",
    "language": "zh",
    "category": "product",
    "ai_score": 5.4,
    "insurance_relevance": 0.45,
    "ai_tags": [],
    "ai_reason": "产品创新：“车电分离”保险加速探路，重塑新能源车险定价逻辑，反映保险产品设计新方向。"
  },
  {
    "title": "新股定价丨白鸽在线今日上市，获242.05倍认购，每股定价15.6港元，暗盘一手赚8500港元",
    "url": "http://hk.eastmoney.com/a/202606293785667085.html",
    "content": "公司与保险公司和场景合作伙伴在保险产品设计及定制方面开展合作。场景险通常指针对特定情况下就特定需求量身定制的合适、短期或保费低的保险产品，为被保险人提供所需保障。该等保险产品具备高度灵活性，保障期限虽短，但涵盖范围广，能渗透至多种分散生活场景，满足特定情境下的保障需求。",
    "source_name": "哈富证券",
    "source_type": "api",
    "published_at": "2026-06-29",
    "category_hint": "product",
    "language": "zh",
    "category": "product",
    "ai_score": 5.3,
    "insurance_relevance": 0.55,
    "ai_tags": [
      "产品"
    ],
    "ai_reason": "产品创新：新股定价丨白鸽在线今日上市，获242.05倍认购，每股定价1，反映保险产品设计新方向。"
  }
]